mbank_csv_export/__init__.py
mbank_csv_export/cli/__init__.py
mbank_csv_export/cli/mbank.py
mbank_csv_export/cli/parser.py
mbank_csv_export/mbank.py
mbank_csv_export/parser.py
mbank_csv_export/settings.py
mbank_csv_export-0.3.0.dist-info/LICENSE
mbank_csv_export-0.3.0.dist-info/METADATA
mbank_csv_export-0.3.0.dist-info/WHEEL
mbank_csv_export-0.3.0.dist-info/entry_points.txt
mbank_csv_export-0.3.0.dist-info/RECORD
