Metadata-Version: 2.1
Name: mbank-csv-export
Version: 0.3.0
Summary: Quick & reliable operations csv exporter for mBank.
Author: Marcin Tyszkiewicz
Author-email: 56219944+mtyszkiewicz@users.noreply.github.com
Requires-Python: >=3.12,<4.0
Classifier: Programming Language :: Python :: 3
Classifier: Programming Language :: Python :: 3.12
Requires-Dist: playwright (>=1.44.0,<2.0.0)
Requires-Dist: pydantic (>=2.9.2,<3.0.0)
Requires-Dist: pydantic-settings (>=2.3.1,<3.0.0)
Requires-Dist: python-dateutil (>=2.9.0.post0,<3.0.0)
